{"id":"o6kk58cac0vvnxzxpfuo3gt","title":"Link","desc":"","updated":1751453456962,"created":1751453456962,"custom":{},"fname":"learning.nextjs.routing.Link","type":"note","vault":{"fsPath":".","selfContained":true,"name":"Harshita-notes","sync":"sync"},"contentHash":"e8e7ec60b5fa9916c73cee47456a7281","links":[],"anchors":{"styling-links":{"type":"header","text":"Styling Links","value":"styling-links","line":31,"column":0,"depth":2},"params":{"type":"header","text":"params","value":"params","line":72,"column":0,"depth":2},"searchparams":{"type":"header","text":"searchParams:","value":"searchparams","line":76,"column":0,"depth":2}},"children":[],"parent":"vh28j803j8gmx35nymyloxt","data":{}}
