{"id":"vh28j803j8gmx35nymyloxt","title":"Routing","desc":"","updated":1750932276890,"created":1750932276890,"custom":{},"fname":"learning.nextjs.routing","type":"note","vault":{"fsPath":".","selfContained":true,"name":"Harshita-notes","sync":"sync"},"contentHash":"fb5b713de7bb620f3db819408c5aa9f3","links":[],"anchors":{"dynamic-routes":{"type":"header","text":"Dynamic routes","value":"dynamic-routes","line":28,"column":0,"depth":2},"nested-dynamic-routes":{"type":"header","text":"Nested dynamic routes","value":"nested-dynamic-routes","line":58,"column":0,"depth":3},"catch-all-segments":{"type":"header","text":"Catch all segments","value":"catch-all-segments","line":62,"column":0,"depth":3}},"children":[],"parent":"val6g08aw70yhmq3ceoda6m","data":{}}
